pygcvs/__init__.py
pygcvs/helpers.py
pygcvs/parser.py
pygcvs-1.1.dist-info/DESCRIPTION.rst
pygcvs-1.1.dist-info/METADATA
pygcvs-1.1.dist-info/RECORD
pygcvs-1.1.dist-info/WHEEL
pygcvs-1.1.dist-info/metadata.json
pygcvs-1.1.dist-info/top_level.txt
